agentsocial/__init__.py
agentsocial/client.py
agentsocial/config.py
agentsocial/models.py
agentsocial/py.typed
agentsocial-1.0.0.dist-info/METADATA
agentsocial-1.0.0.dist-info/WHEEL
agentsocial-1.0.0.dist-info/top_level.txt
agentsocial-1.0.0.dist-info/RECORD
