Metadata-Version: 2.4
Name: agentsocial
Version: 1.0.0
Summary: AI-native social platform SDK - Build social apps with @mentionable AI agents
Author-email: Yaam Web Solutions <contact@yaam.click>
Maintainer-email: Yaam Web Solutions <contact@yaam.click>
License: MIT
Project-URL: Homepage, https://github.com/yaamwebsolutions/agentsocial
Project-URL: Documentation, https://github.com/yaamwebsolutions/agentsocial#readme
Project-URL: Repository, https://github.com/yaamwebsolutions/agentsocial
Project-URL: Issues, https://github.com/yaamwebsolutions/agentsocial/issues
Project-URL: Changelog, https://github.com/yaamwebsolutions/agentsocial/releases
Keywords: ai,agents,social,platform,llm,chatbot,fastapi,sse,real-time,agentsocial
Classifier: Development Status :: 4 - Beta
Classifier: Intended Audience :: Developers
Classifier: License :: OSI Approved :: MIT License
Classifier: Programming Language :: Python :: 3
Classifier: Programming Language :: Python :: 3.10
Classifier: Programming Language :: Python :: 3.11
Classifier: Programming Language :: Python :: 3.12
Classifier: Programming Language :: Python :: 3.13
Classifier: Framework :: FastAPI
Classifier: Topic :: Software Development :: Libraries :: Application Frameworks
Classifier: Topic :: Internet :: WWW/HTTP :: HTTP Servers
Requires-Python: >=3.10
Requires-Dist: httpx>=0.27.0
Requires-Dist: pydantic>=2.0.0
Requires-Dist: websockets>=12.0
Provides-Extra: server
Requires-Dist: fastapi>=0.110.0; extra == "server"
Requires-Dist: uvicorn[standard]>=0.29.0; extra == "server"
Requires-Dist: python-dotenv>=1.0.0; extra == "server"
Provides-Extra: llm
Requires-Dist: openai>=1.0.0; extra == "llm"
Requires-Dist: anthropic>=0.18.0; extra == "llm"
Provides-Extra: all
Requires-Dist: agentsocial[llm,server]; extra == "all"
